delayed_rm/__init__.py
delayed_rm/delayed_rm.py
delayed_rm/py.typed
delayed_rm-3.0.2.dist-info/licenses/LICENSE
delayed_rm-3.0.2.dist-info/METADATA
delayed_rm-3.0.2.dist-info/WHEEL
delayed_rm-3.0.2.dist-info/entry_points.txt
delayed_rm-3.0.2.dist-info/top_level.txt
delayed_rm-3.0.2.dist-info/RECORD
