Metadata-Version: 2.4
Name: delayed_rm
Version: 3.0.2
Summary: Ever wish you had a few minutes to undo an rm? Now you do!
License: GPLv3
Project-URL: Homepage, https://github.com/zwimer/delayed_rm
Keywords: rm
Classifier: Programming Language :: Python :: 3
Classifier: Programming Language :: Python :: 3.12
Classifier: Development Status :: 5 - Production/Stable
Classifier: License :: OSI Approved :: GNU General Public License v3 (GPLv3)
Requires-Python: >=3.12
License-File: LICENSE
Dynamic: license-file
